baseconvertpy/__init__.py
baseconvertpy/base_change.py
baseconvertpy-1.0.2.dist-info/METADATA
baseconvertpy-1.0.2.dist-info/WHEEL
baseconvertpy-1.0.2.dist-info/top_level.txt
baseconvertpy-1.0.2.dist-info/RECORD
