Metadata-Version: 2.1
Name: baseconvertpy
Version: 1.0.2
Summary: A simple way to convert numbers from one base to another.
Home-page: https://github.com/Siddharth3141/BaseConvertPy
Author: Siddharth
License: MIT
Keywords: python,base,conversion,number
Platform: UNKNOWN
Classifier: Programming Language :: Python :: 3
